docs/conf.py
examples/basic_usage.py
examples/rtd_tutorial.py
examples/tutorial.py
examples/publication/1_salivary_gland_tumors.py
examples/publication/2_soft_tissue_tumors.py
examples/publication/3_scc.py
examples/publication/4_cns_tumors.py
mepylome/__init__.py
mepylome/cli.py
mepylome/analysis/__init__.py
mepylome/analysis/methyl.py
mepylome/analysis/methyl_aux.py
mepylome/analysis/methyl_clf.py
mepylome/analysis/methyl_plots.py
mepylome/data/config.toml
mepylome/data/gaps.csv.gz
mepylome/data/gene_loci_epicv2.tsv.gz
mepylome/data/methylation_class_acronyms.tsv.gz
mepylome/data/tutorial.csv.gz
mepylome/data/assets/dropdown.css
mepylome/data/assets/favicon.svg
mepylome/data/assets/mepylome.svg
mepylome/data/assets/mepylome_raw.svg
mepylome/dtypes/__init__.py
mepylome/dtypes/arrays.py
mepylome/dtypes/beads.py
mepylome/dtypes/cache.py
mepylome/dtypes/chromosome.py
mepylome/dtypes/cnv.py
mepylome/dtypes/idat.py
mepylome/dtypes/manifests.py
mepylome/dtypes/plots.py
mepylome/dtypes/probes.py
mepylome/tests/__init__.py
mepylome/tests/helpers.py
mepylome/tests/write_idat.py
mepylome/utils/__init__.py
mepylome/utils/downloader.py
mepylome/utils/files.py
mepylome/utils/varia.py
mepylome-0.10.0.dist-info/licenses/LICENSE
scripts/convert_py_to_rst.py
scripts/make_gene_annotation.py
scripts/diagnostics/run_methylation_diagnostics.py
tests/test_beads.py
tests/test_idat.py
tests/test_manifests.py
tests/benchmark/benchmark_cnv.py
tests/benchmark/benchmark_idat_extraction.py
tests/benchmark/correctness.py
tests/benchmark/swan.py
trash/profile_script.py
trash/test.py
trash/trash.py
trash/trash_clf.py
trash/trashpaste.py
mepylome-0.10.0.dist-info/METADATA
mepylome-0.10.0.dist-info/WHEEL
mepylome-0.10.0.dist-info/entry_points.txt
mepylome-0.10.0.dist-info/top_level.txt
mepylome-0.10.0.dist-info/RECORD
