Metadata-Version: 2.4
Name: mepylome
Version: 0.10.0
Summary: Python package for processing Infinum DNA methylation arrays
Author: Jon Brugger
License-Expression: MIT
Project-URL: Homepage, https://github.com/brj0/mepylome
Keywords: Illumina,Methylation,Infinum,Microarray,BeadChip
Classifier: Development Status :: 3 - Alpha
Classifier: Intended Audience :: Developers
Classifier: Intended Audience :: Science/Research
Classifier: Operating System :: POSIX
Classifier: Programming Language :: Python :: 3
Classifier: Topic :: Scientific/Engineering
Classifier: Topic :: Software Development
Requires-Python: >=3.10
License-File: LICENSE
Requires-Dist: dash<3.1.0,>=2.16.0
Requires-Dist: dash_bootstrap_components
Requires-Dist: numpy
Requires-Dist: odfpy
Requires-Dist: openpyxl
Requires-Dist: pandas
Requires-Dist: plotly<6.0.0
Requires-Dist: psutil
Requires-Dist: pyranges<0.1.3
Requires-Dist: scikit-learn
Requires-Dist: tqdm
Requires-Dist: toml
Requires-Dist: umap-learn
Requires-Dist: numba<0.62
Requires-Dist: xlrd
Requires-Dist: xxhash
Provides-Extra: seg
Requires-Dist: ruptures; extra == "seg"
Provides-Extra: dev
Requires-Dist: build; extra == "dev"
Requires-Dist: ipython; extra == "dev"
Requires-Dist: ipywidgets; extra == "dev"
Requires-Dist: jupyter; extra == "dev"
Requires-Dist: jupytext; extra == "dev"
Requires-Dist: kaleido==0.2.1; extra == "dev"
Requires-Dist: mypy; extra == "dev"
Requires-Dist: nbstripout; extra == "dev"
Requires-Dist: pillow; extra == "dev"
Requires-Dist: pytest; extra == "dev"
Requires-Dist: ruff; extra == "dev"
Requires-Dist: ruptures; extra == "dev"
Requires-Dist: sphinx; extra == "dev"
Requires-Dist: sphinx-rtd-theme; extra == "dev"
Requires-Dist: tuna; extra == "dev"
Requires-Dist: twine; extra == "dev"
Requires-Dist: ty; extra == "dev"
Dynamic: license-file
